attachmentav/__init__.py
attachmentav/api_client.py
attachmentav/api_response.py
attachmentav/configuration.py
attachmentav/exceptions.py
attachmentav/py.typed
attachmentav/rest.py
attachmentav/api/__init__.py
attachmentav/api/attachment_av_api.py
attachmentav/models/__init__.py
attachmentav/models/async_download_scan_request.py
attachmentav/models/async_s3_scan_request.py
attachmentav/models/scan_result.py
attachmentav/models/sync_download_scan_request.py
attachmentav/models/sync_s3_scan_request.py
attachmentav/models/usage.py
attachmentav/models/usage_quota.py
attachmentav/models/whoami.py
attachmentav_virus_malware_scan_sdk-0.4.0.dist-info/METADATA
attachmentav_virus_malware_scan_sdk-0.4.0.dist-info/WHEEL
attachmentav_virus_malware_scan_sdk-0.4.0.dist-info/top_level.txt
attachmentav_virus_malware_scan_sdk-0.4.0.dist-info/RECORD
