Metadata-Version: 2.4
Name: attachmentav_virus_malware_scan_sdk
Version: 0.4.0
Summary: A virus scan SDK for Python. Scan files for viruses, trojans, and other kinds of malware with attachmentAV.
Home-page: https://github.com/widdix/attachmentav-sdk-python
Author: Andreas Wittig
Author-email: Andreas Wittig <andreas@attachmentav.com>
License-Expression: MIT
Project-URL: Repository, https://github.com/widdix/attachmentav-sdk-python
Keywords: virus,malware,scan,scanner,sdk
Requires-Python: >=3.9
Requires-Dist: urllib3<3.0.0,>=2.1.0
Requires-Dist: python-dateutil>=2.8.2
Requires-Dist: pydantic>=2
Requires-Dist: typing-extensions>=4.7.1
Dynamic: author
Dynamic: home-page
